rubin_jupyter_utils/helpers/__init__.py
rubin_jupyter_utils/helpers/_version.py
rubin_jupyter_utils/helpers/groups.py
rubin_jupyter_utils/helpers/k8s.py
rubin_jupyter_utils/helpers/log.py
rubin_jupyter_utils/helpers/moneypenny.py
rubin_jupyter_utils/helpers/singleton.py
rubin_jupyter_utils/helpers/token.py
rubin_jupyter_utils/helpers/typehelpers.py
rubin_jupyter_utils/helpers/static/moneypenny-jwt-template.json
rubin_jupyter_utils.helpers-0.33.0.dist-info/LICENSE
rubin_jupyter_utils.helpers-0.33.0.dist-info/METADATA
rubin_jupyter_utils.helpers-0.33.0.dist-info/WHEEL
rubin_jupyter_utils.helpers-0.33.0.dist-info/top_level.txt
rubin_jupyter_utils.helpers-0.33.0.dist-info/RECORD
