Metadata-Version: 2.1
Name: rubin-jupyter-utils.helpers
Version: 0.33.0
Summary: UNKNOWN
Home-page: https://github.com/lsst-sqre/rubin-jupyter-helpers
Author: Adam Thornton
Author-email: athornton@lsst.org
License: MIT
Keywords: lsst
Platform: UNKNOWN
Classifier: Development Status :: 4 - Beta
Classifier: Programming Language :: Python :: 2.7
Classifier: Programming Language :: Python :: 3.5
Classifier: License :: OSI Approved :: MIT License
Requires-Dist: eliot
Requires-Dist: kubernetes
Requires-Dist: pyjwt
Requires-Dist: requests (<3,>=2)
